hellowww/__init__.py
hellowww/hello.py
hellowww-0.0.1.dist-info/LICENSE
hellowww-0.0.1.dist-info/METADATA
hellowww-0.0.1.dist-info/WHEEL
hellowww-0.0.1.dist-info/top_level.txt
hellowww-0.0.1.dist-info/RECORD
